{
  "data": {
    "items": [
      {
        "unixTime": 1745067600,
        "value": 0.032989804654867665
      },
      {
        "unixTime": 1745071200,
        "value": 0.03281346023566436
      },
      {
        "unixTime": 1745074800,
        "value": 0.03303713523552266
      },
      {
        "unixTime": 1745078400,
        "value": 0.03252991340489933
      },
      {
        "unixTime": 1745082000,
        "value": 0.03356240724494764
      },
      {
        "unixTime": 1745085600,
        "value": 0.034173438619115634
      },
      {
        "unixTime": 1745089200,
        "value": 0.03323297005061991
      },
      {
        "unixTime": 1745092800,
        "value": 0.033804126437705605
      },
      {
        "unixTime": 1745096400,
        "value": 0.034103913765862116
      },
      {
        "unixTime": 1745100000,
        "value": 0.034422586001285886
      },
      {
        "unixTime": 1745103600,
        "value": 0.034461488378859526
      },
      {
        "unixTime": 1745107200,
        "value": 0.0343178180988463
      },
      {
        "unixTime": 1745110800,
        "value": 0.034796288785221764
      },
      {
        "unixTime": 1745114400,
        "value": 0.035195661009890473
      },
      {
        "unixTime": 1745118000,
        "value": 0.03577189240806884
      },
      {
        "unixTime": 1745121600,
        "value": 0.03727836066457037
      },
      {
        "unixTime": 1745125200,
        "value": 0.03656500424460705
      },
      {
        "unixTime": 1745128800,
        "value": 0.03682352485054988
      },
      {
        "unixTime": 1745132400,
        "value": 0.03627796089728795
      },
      {
        "unixTime": 1745136000,
        "value": 0.0365754258585555
      },
      {
        "unixTime": 1745139600,
        "value": 0.0357664459127297
      },
      {
        "unixTime": 1745143200,
        "value": 0.03526682815332502
      },
      {
        "unixTime": 1745146800,
        "value": 0.03528203249623017
      },
      {
        "unixTime": 1745150400,
        "value": 0.03590154387869219
      },
      {
        "unixTime": 1745154000,
        "value": 0.035769284741035676
      },
      {
        "unixTime": 1745157600,
        "value": 0.03573887405142573
      },
      {
        "unixTime": 1745161200,
        "value": 0.03541509177490034
      },
      {
        "unixTime": 1745164800,
        "value": 0.03564796976156369
      },
      {
        "unixTime": 1745168400,
        "value": 0.03495324854570033
      },
      {
        "unixTime": 1745172000,
        "value": 0.03539308233043611
      },
      {
        "unixTime": 1745175600,
        "value": 0.035753723629941746
      },
      {
        "unixTime": 1745179200,
        "value": 0.03564499638771253
      },
      {
        "unixTime": 1745182800,
        "value": 0.03577254354809359
      },
      {
        "unixTime": 1745186400,
        "value": 0.03514093331774421
      },
      {
        "unixTime": 1745190000,
        "value": 0.035862472118522275
      },
      {
        "unixTime": 1745193600,
        "value": 0.03652863389119726
      },
      {
        "unixTime": 1745197200,
        "value": 0.036830169639191036
      },
      {
        "unixTime": 1745200800,
        "value": 0.0361848884499457
      },
      {
        "unixTime": 1745204400,
        "value": 0.03586049539008955
      },
      {
        "unixTime": 1745208000,
        "value": 0.03624330517297917
      },
      {
        "unixTime": 1745211600,
        "value": 0.03606024633449977
      },
      {
        "unixTime": 1745215200,
        "value": 0.03555566064654606
      },
      {
        "unixTime": 1745218800,
        "value": 0.03557312210939398
      },
      {
        "unixTime": 1745222400,
        "value": 0.03637120944176356
      },
      {
        "unixTime": 1745226000,
        "value": 0.036475727854783827
      },
      {
        "unixTime": 1745229600,
        "value": 0.03611399518304894
      },
      {
        "unixTime": 1745233200,
        "value": 0.035303792634038274
      },
      {
        "unixTime": 1745236800,
        "value": 0.03534427734049744
      },
      {
        "unixTime": 1745240400,
        "value": 0.03517435172273497
      },
      {
        "unixTime": 1745244000,
        "value": 0.03646858075772146
      },
      {
        "unixTime": 1745247600,
        "value": 0.03582897398754744
      },
      {
        "unixTime": 1745251200,
        "value": 0.034138114308748066
      },
      {
        "unixTime": 1745254800,
        "value": 0.03415524777278865
      },
      {
        "unixTime": 1745258400,
        "value": 0.03523755662572077
      },
      {
        "unixTime": 1745262000,
        "value": 0.03551119672397418
      },
      {
        "unixTime": 1745265600,
        "value": 0.03537797352084231
      },
      {
        "unixTime": 1745269200,
        "value": 0.03483305058922768
      },
      {
        "unixTime": 1745272800,
        "value": 0.03457395263167941
      },
      {
        "unixTime": 1745276400,
        "value": 0.03514272182557897
      },
      {
        "unixTime": 1745280000,
        "value": 0.034912390857385844
      },
      {
        "unixTime": 1745283600,
        "value": 0.03675827006790017
      },
      {
        "unixTime": 1745287200,
        "value": 0.03663380285852635
      },
      {
        "unixTime": 1745290800,
        "value": 0.0360164076187961
      },
      {
        "unixTime": 1745294400,
        "value": 0.03776312995634169
      },
      {
        "unixTime": 1745298000,
        "value": 0.03743733003360067
      },
      {
        "unixTime": 1745301600,
        "value": 0.036608261487057064
      },
      {
        "unixTime": 1745305200,
        "value": 0.037485146607239735
      },
      {
        "unixTime": 1745308800,
        "value": 0.03725570738140887
      },
      {
        "unixTime": 1745312400,
        "value": 0.036821681733178895
      },
      {
        "unixTime": 1745316000,
        "value": 0.037735237167290776
      },
      {
        "unixTime": 1745319600,
        "value": 0.03808909835257169
      },
      {
        "unixTime": 1745323200,
        "value": 0.03995358676089074
      },
      {
        "unixTime": 1745326800,
        "value": 0.04194681911353448
      },
      {
        "unixTime": 1745330400,
        "value": 0.04505454463611329
      },
      {
        "unixTime": 1745334000,
        "value": 0.045958670777960876
      },
      {
        "unixTime": 1745337600,
        "value": 0.045837377757187894
      },
      {
        "unixTime": 1745341200,
        "value": 0.045602113316317146
      },
      {
        "unixTime": 1745344800,
        "value": 0.04564898776389189
      },
      {
        "unixTime": 1745348400,
        "value": 0.046407148085791154
      },
      {
        "unixTime": 1745352000,
        "value": 0.04636900518171087
      },
      {
        "unixTime": 1745355600,
        "value": 0.04861594581013438
      },
      {
        "unixTime": 1745359200,
        "value": 0.053843364002176576
      },
      {
        "unixTime": 1745362800,
        "value": 0.05509895142753779
      },
      {
        "unixTime": 1745366400,
        "value": 0.055078973981969585
      },
      {
        "unixTime": 1745370000,
        "value": 0.053295036891231315
      },
      {
        "unixTime": 1745373600,
        "value": 0.05513294246227423
      },
      {
        "unixTime": 1745377200,
        "value": 0.05533490516844901
      },
      {
        "unixTime": 1745380800,
        "value": 0.05788212277673026
      },
      {
        "unixTime": 1745384400,
        "value": 0.057381179606840096
      },
      {
        "unixTime": 1745388000,
        "value": 0.05515835337737223
      },
      {
        "unixTime": 1745391600,
        "value": 0.05539956975582868
      },
      {
        "unixTime": 1745395200,
        "value": 0.0555701331096567
      },
      {
        "unixTime": 1745398800,
        "value": 0.05478890198141305
      },
      {
        "unixTime": 1745402400,
        "value": 0.055244185412127514
      },
      {
        "unixTime": 1745406000,
        "value": 0.05506787966706518
      },
      {
        "unixTime": 1745409600,
        "value": 0.0567886570896591
      },
      {
        "unixTime": 1745413200,
        "value": 0.05580385388729177
      },
      {
        "unixTime": 1745416800,
        "value": 0.05569861100816156
      },
      {
        "unixTime": 1745420400,
        "value": 0.056306889840976045
      },
      {
        "unixTime": 1745424000,
        "value": 0.05077618220243544
      }
    ]
  },
  "success": true
}
