{
  "data": {
    "items": [
      {
        "unixTime": 1744912800,
        "value": 0.00007017087272475409
      },
      {
        "unixTime": 1744916400,
        "value": 0.0001727222650018098
      },
      {
        "unixTime": 1744920000,
        "value": 0.0002032331455344175
      },
      {
        "unixTime": 1744923600,
        "value": 0.00018672320704945424
      },
      {
        "unixTime": 1744927200,
        "value": 0.00020152923751023662
      },
      {
        "unixTime": 1744930800,
        "value": 0.0001962583801067854
      },
      {
        "unixTime": 1744934400,
        "value": 0.00018980539366885858
      },
      {
        "unixTime": 1744938000,
        "value": 0.00019860752371827307
      },
      {
        "unixTime": 1744941600,
        "value": 0.00017394496252008646
      },
      {
        "unixTime": 1744945200,
        "value": 0.00014791430284011482
      },
      {
        "unixTime": 1744948800,
        "value": 0.00015278036829576336
      },
      {
        "unixTime": 1744952400,
        "value": 0.00016290431411179269
      },
      {
        "unixTime": 1744956000,
        "value": 0.00014949766907559181
      },
      {
        "unixTime": 1744959600,
        "value": 0.00017278084505068932
      },
      {
        "unixTime": 1744963200,
        "value": 0.00015434134870412523
      },
      {
        "unixTime": 1744966800,
        "value": 0.00014423295522250268
      },
      {
        "unixTime": 1744970400,
        "value": 0.0000940654348363844
      },
      {
        "unixTime": 1744974000,
        "value": 0.00010803209247738213
      },
      {
        "unixTime": 1744977600,
        "value": 0.00010420145751946857
      },
      {
        "unixTime": 1744981200,
        "value": 0.0001764613257597363
      },
      {
        "unixTime": 1744984800,
        "value": 0.0001952659010513284
      },
      {
        "unixTime": 1744988400,
        "value": 0.00013099280132827847
      },
      {
        "unixTime": 1744992000,
        "value": 0.00011400994421581887
      },
      {
        "unixTime": 1744995600,
        "value": 0.0001287195897756489
      }
    ]
  },
  "success": true
}
